[
  { "id": "youtube", "name": "YouTube", "icon": "YoutubeLogoIcon" },
  { "id": "x", "name": "X / Twitter", "icon": "XLogoIcon" },
  { "id": "instagram", "name": "Instagram", "icon": "InstagramLogoIcon" },
  { "id": "linkedin", "name": "LinkedIn", "icon": "LinkedinLogoIcon" },
  { "id": "spotify", "name": "Spotify", "icon": "SpotifyLogoIcon" },
  { "id": "github", "name": "GitHub", "icon": "GithubLogoIcon" },
  { "id": "discord", "name": "Discord", "icon": "DiscordLogoIcon" },
  { "id": "figma", "name": "Figma", "icon": "FigmaLogoIcon" },
  { "id": "twitch", "name": "Twitch", "icon": "TwitchLogoIcon" },
  { "id": "tiktok", "name": "TikTok", "icon": "TiktokLogoIcon" },
  { "id": "reddit", "name": "Reddit", "icon": "RedditLogoIcon" },
  { "id": "goodreads", "name": "Goodreads", "icon": "GoodreadsLogoIcon" },
  { "id": "medium", "name": "Medium", "icon": "MediumLogoIcon" },
  { "id": "substack", "name": "Substack", "icon": "NewspaperIcon" }
]
